[
   {
      "cost_score":25.0,
      "country":"US",
      "covid_info":{
         "city":"Los_Angeles",
         "date":"2020-11-17T16:08:39.395Z",
         "latest_data":{
            "calculated":{
               "cases_per_million_population":21202,
               "death_rate":2.1892757373125438,
               "recovered_vs_death_ratio":"None",
               "recovery_rate":60.81891094750442
            },
            "confirmed":11548020,
            "critical":4271822,
            "deaths":252818,
            "recovered":7023380
         },
         "today":{
            "confirmed":9740,
            "deaths":166
         }
      },
      "distance":9088.16019369436,
      "distance_score":2,
      "id":"8",
      "img_url":"upload.wikimedia.org/wikipedia/commons/thumb/6/69/Los_Angeles_with_Mount_Baldy.jpg/800px-Los_Angeles_with_Mount_Baldy.jpg",
      "name":"Los_Angeles",
      "score":84.54810495626823,
      "tag_score":160.0,
      "weather":{
         "temperature":17,
         "weather":[
            {
               "description":"clear sky",
               "icon":"01d",
               "id":800,
               "main":"Clear"
            }
         ]
      },
      "weather_score":48.0
   },
   {
      "cost_score":50.0,
      "country":"SA",
      "covid_info":{
         "city":"Riyadh",
         "date":"2020-11-17T16:04:32.267Z",
         "latest_data":{
            "calculated":{
               "cases_per_million_population":816,
               "death_rate":1.6082821444515398,
               "recovered_vs_death_ratio":"None",
               "recovery_rate":96.3793873157059
            },
            "confirmed":353918,
            "critical":7122,
            "deaths":5692,
            "recovered":341104
         },
         "today":{
            "confirmed":362,
            "deaths":16
         }
      },
      "distance":4688.129282112144,
      "distance_score":4,
      "id":"60",
      "img_url":"upload.wikimedia.org/wikipedia/commons/thumb/1/1a/Riyadh%2C_Saudi_Arabia_%282048x1367%29_%2836864830374%29.jpg/800px-Riyadh%2C_Saudi_Arabia_%282048x1367%29_%2836864830374%29.jpg",
      "name":"Riyadh",
      "score":86.0058309037901,
      "tag_score":135.0,
      "weather":{
         "temperature":26,
         "weather":[
            {
               "description":"clear sky",
               "icon":"01n",
               "id":800,
               "main":"Clear"
            }
         ]
      },
      "weather_score":48.0
   }
]